{"singlePage": ["about"], "startSite": "07/24/2024", "filingNum": "", "onePageListNum": 15, "commentLabelColor": "#006b75", "yearColorList": ["#bc4c00", "#0969da", "#1f883d", "#A333D0"], "i18n": "CN", "themeMode": "manual", "dayTheme": "light", "nightTheme": "dark_colorblind", "urlMode": "pinyin", "script": "<script src='https://blog.meekdai.com/Gmeek/plugins/articletoc.js'></script><script src='https://blog.meekdai.com/Gmeek/plugins/lightbox.js'></script>", "style": "", "head": "", "indexScript": "", "indexStyle": "", "bottomText": "\u8f6c\u8f7d\u8bf7\u6ce8\u660e\u51fa\u5904", "showPostSource": 1, "iconList": {}, "UTC": 8, "rssSplit": "sentence", "exlink": {}, "needComment": 1, "allHead": "<script src='https://blog.meekdai.com/Gmeek/plugins/GmeekBSZ.js'></script> <script src='https://blog.meekdai.com/Gmeek/plugins/GmeekVercount.js'></script> <meta name='google-site-verification' content='1VMjcA03zLI8aKEYQ3WOXgkTtOBe--5NNn6YKpeAxzQ' /> <script async src='https://www.googletagmanager.com/gtag/js?id=G-ESWXK6HG1Q'></script><script>window.dataLayer = window.dataLayer || [];function gtag(){dataLayer.push(arguments);}gtag('js', new Date());gtag('config', 'G-ESWXK6HG1Q');</script>", "title": "Passi0n1's Blog", "subTitle": "\u4e16\u754c\u662f\u6211\u4eec\u7684\u6e38\u4e50\u573a", "avatarUrl": "https://avatars.githubusercontent.com/u/181446367?v=4", "GMEEK_VERSION": "last", "postListJson": {"P1": {"htmlDir": "docs/post/hello.html", "labels": ["test"], "postTitle": "hello", "postUrl": "post/hello.html", "postSourceUrl": "https://github.com/Passi0n1/Passi0n1.github.io/issues/1", "commentNum": 1, "wordCount": 212, "description": "hello\uff0cworld\r\n\r\n\r\n\r\nThis message is used to verify that this feed (feedId:61649528611678208) belongs to me (userId:61646731125452800). Join me in enjoying the next generation information browser https://follow.is.\u3002", "top": 0, "createdAt": 1726208929, "style": "", "script": "<script src='https://blog.meekdai.com/Gmeek/plugins/articletoc.js'></script><script src='https://blog.meekdai.com/Gmeek/plugins/lightbox.js'></script>", "head": "", "ogImage": "https://avatars.githubusercontent.com/u/181446367?v=4", "createdDate": "2024-09-13", "dateLabelColor": "#bc4c00"}, "P2": {"htmlDir": "docs/post/payable\u3001view-he- pure.html", "labels": ["Smart contract"], "postTitle": "payable\u3001view\u548c pure", "postUrl": "post/payable%E3%80%81view-he-%20pure.html", "postSourceUrl": "https://github.com/Passi0n1/Passi0n1.github.io/issues/2", "commentNum": 0, "wordCount": 1766, "description": "`payable` \u6b64\u5173\u952e\u5b57\u53ef\u4ee5\u8bf4\u660e\u67d0\u4e2a\u51fd\u6570\u53ef\u4ee5\u63a5\u6536 ETH\r\n\r\n```\r\ncontract PaymentContract {\r\n    function receivePayment() public payable {\r\n        // \u8fd9\u91cc\u53ef\u4ee5\u8bb0\u5f55\u652f\u4ed8\u4fe1\u606f\u6216\u6267\u884c\u5176\u4ed6\u64cd\u4f5c\r\n    }\r\n}\r\n```\r\n\r\n`pure`  \u65e2\u4e0d\u80fd\u8bfb\uff0c\u4e5f\u4e0d\u80fd\u5199\uff0c\u53ea\u9002\u5408\u7528\u6765\u6807\u8bb0\u54ea\u4e9b\u4e0d\u4f1a\u6539\u53d8\u5185\u5bb9\u7684\u51fd\u6570\u3002", "top": 0, "createdAt": 1727184857, "style": "", "script": "<script src='https://blog.meekdai.com/Gmeek/plugins/articletoc.js'></script><script src='https://blog.meekdai.com/Gmeek/plugins/lightbox.js'></script>", "head": "", "ogImage": "https://avatars.githubusercontent.com/u/181446367?v=4", "createdDate": "2024-09-24", "dateLabelColor": "#bc4c00"}, "P3": {"htmlDir": "docs/post/jie-gou-shi-fu-zhi.html", "labels": ["Smart contract"], "postTitle": "\u89e3\u6784\u5f0f\u8d4b\u503c", "postUrl": "post/jie-gou-shi-fu-zhi.html", "postSourceUrl": "https://github.com/Passi0n1/Passi0n1.github.io/issues/3", "commentNum": 0, "wordCount": 1576, "description": "\u89e3\u6784\u5f0f\u6307\u7684\u662f\u5c06\u591a\u7ef4\u3001\u591a\u4e2a\u7684\u53c2\u6570\u4f4d\u540c\u65f6\u6279\u91cf\uff08\u5f53\u7136\uff0c\u4e5f\u53ef\u4ee5\u4eba\u4e3a\u7b5b\u9009\u6389\u4e00\u4e9b\u53c2\u6570\u4e0d\u53bb\u8fdb\u884c\u590d\u5236\uff09\r\n```\r\nuint256 _number;\r\nbool _bool;\r\nuint256[3] memory _array;\r\n(_number, _bool, _array) = returnNamed();\r\n```\r\n\u5728\u8fd9\u4e2a\u6848\u4f8b\u5f53\u4e2d\uff0c\u5148\u58f0\u660e\u53d8\u91cf\uff0c\u7136\u540e\u5c06 `returnNamed` \u8fd0\u884c\u7684\u7ed3\u679c\u53cd\u9988\u8d4b\u503c\u5230\u8fd9\u4e09\u4e2a\u53c2\u6570\u4e0a\u9762\u3002", "top": 0, "createdAt": 1727184913, "style": "", "script": "<script src='https://blog.meekdai.com/Gmeek/plugins/articletoc.js'></script><script src='https://blog.meekdai.com/Gmeek/plugins/lightbox.js'></script>", "head": "", "ogImage": "https://avatars.githubusercontent.com/u/181446367?v=4", "createdDate": "2024-09-24", "dateLabelColor": "#bc4c00"}, "P4": {"htmlDir": "docs/post/qu-kuai-lian-zhong-de-cun-chu-lei-xing.html", "labels": ["Smart contract"], "postTitle": "\u533a\u5757\u94fe\u4e2d\u7684\u5b58\u50a8\u7c7b\u578b", "postUrl": "post/qu-kuai-lian-zhong-de-cun-chu-lei-xing.html", "postSourceUrl": "https://github.com/Passi0n1/Passi0n1.github.io/issues/4", "commentNum": 0, "wordCount": 3844, "description": "## Storage\r\nstorage \u5b58\u50a8\u7684\u662f\u58f0\u660e\u5b9a\u4e49\u7684\u6570\u636e\u3002", "top": 0, "createdAt": 1727352580, "style": "", "script": "<script src='https://blog.meekdai.com/Gmeek/plugins/articletoc.js'></script><script src='https://blog.meekdai.com/Gmeek/plugins/lightbox.js'></script>", "head": "", "ogImage": "https://avatars.githubusercontent.com/u/181446367?v=4", "createdDate": "2024-09-26", "dateLabelColor": "#bc4c00"}, "P5": {"htmlDir": "docs/post/he-yue-zhong-de-event.html", "labels": ["Smart contract"], "postTitle": "\u5408\u7ea6\u4e2d\u7684event", "postUrl": "post/he-yue-zhong-de-event.html", "postSourceUrl": "https://github.com/Passi0n1/Passi0n1.github.io/issues/5", "commentNum": 0, "wordCount": 3436, "description": "**\u4e8b\u4ef6**\r\nenevt \u662f\u4e2a\u88ab\u5b9a\u4e49\u7684\u4e8b\u4ef6\uff0c\u4e3b\u8981\u7684\u529f\u80fd\u7684\u5bf9\u5916\u5c55\u793a\u548c\u8bb0\u5f55\u4f5c\u7528\uff0c\u5e76\u4e0d\u662f\u771f\u6b63\u7684\u4ee3\u7801\u7684\u6267\u884c\u3002", "top": 0, "createdAt": 1727438847, "style": "", "script": "<script src='https://blog.meekdai.com/Gmeek/plugins/articletoc.js'></script><script src='https://blog.meekdai.com/Gmeek/plugins/lightbox.js'></script>", "head": "", "ogImage": "https://avatars.githubusercontent.com/u/181446367?v=4", "createdDate": "2024-09-27", "dateLabelColor": "#bc4c00"}}, "singeListJson": {}, "labelColorDict": {"Smart contract": "#787642", "test": "#BE9527"}, "displayTitle": "Passi0n1's Blog", "faviconUrl": "https://avatars.githubusercontent.com/u/181446367?v=4", "ogImage": "https://avatars.githubusercontent.com/u/181446367?v=4", "primerCSS": "<link href='https://mirrors.sustech.edu.cn/cdnjs/ajax/libs/Primer/21.0.7/primer.css' rel='stylesheet' />", "homeUrl": "https://Passi0n1.github.io", "prevUrl": "disabled", "nextUrl": "disabled"}